[
    {
        "title": "Десерты, выпечка",
        "description": "Без них невозможно представить себе ни современную, ни традиционную кулинарию. Пироги и печенья, блины, пончики, вареники и, конечно, хлеб — рецепты изделий из теста многообразны и невероятно популярны.",
        "base": [
            {
                "subcategory": "second-dish",
                "badgeIcon": "/src/assets/icons/pan.svg",
                "title": "Хачапури по-аджарски",
                "description": "Давно ходил вокруг рецепта хачапури по-аджарски, не решался. Сегодня попробовал - я в полном восторге! Тесто замечательное, интересный процесс приготовления, а вкус - не передать, просто сказка!",
                "likes": 1,
                "bookmarks": 1
            },
            {
                "subcategory": "second-dish",
                "badgeIcon": "/src/assets/icons/pan.svg",
                "title": "Жареные сосиски в тесте",
                "description": "Сосиски, жареные в тесте, - звучит уже аппетитно! Тончайшая румяная корочка, воздушное дрожжевое тесто, сочная сосиска... Мало кто может устоять перед такими вот пирожочками, особенно домашнего приготовления. Да, жареные в тесте сосиски",
                "likes": 1,
                "bookmarks": 2
            }
        ],
        "compact": [
            {
                "icon": "/src/assets/icons/pan.svg",
                "title": "Стейк для вегетарианцев"
            },
            {
                "icon": "/src/assets/icons/pan.svg",
                "title": "Котлеты из гречки и фасоли"
            },
            {
                "icon": "/src/assets/icons/pot.svg",
                "title": "Сырный суп с лапшой и брокколи"
            }
        ]
    }
]
